{"BackgroundName":"Background1","star3":30,"star2":20,"items":[{"name":"VeryLongHouse","posX":-0.5,"posY":-1.5,"rotX":0.0,"rotY":0.0,"rotZ":0.0,"scaleX":0.0,"scaleY":0.0},{"name":"Steel","posX":9.5,"posY":0.0,"rotX":0.0,"rotY":0.0,"rotZ":0.0,"scaleX":0.0,"scaleY":0.0},{"name":"ElectricOBstacle","posX":6.5,"posY":1.0,"rotX":0.0,"rotY":0.0,"rotZ":0.0,"scaleX":0.0,"scaleY":0.0},{"name":"ElectricOBstacle","posX":6.980000019073486,"posY":0.3700000047683716,"rotX":0.0,"rotY":0.0,"rotZ":0.0,"scaleX":0.0,"scaleY":0.0},{"name":"ElectricOBstacle","posX":53.970001220703128,"posY":-1.0399999618530274,"rotX":0.0,"rotY":0.0,"rotZ":0.0,"scaleX":0.0,"scaleY":0.0},{"name":"Pipe","posX":23.0,"posY":2.0,"rotX":0.0,"rotY":0.0,"rotZ":0.0,"scaleX":0.0,"scaleY":0.0},{"name":"Saw","posX":9.5,"posY":0.5,"rotX":0.0,"rotY":0.0,"rotZ":0.0,"scaleX":0.0,"scaleY":0.0},{"name":"Coin","posX":11.5,"posY":1.0,"rotX":0.0,"rotY":0.0,"rotZ":0.0,"scaleX":0.0,"scaleY":0.0},{"name":"Coin","posX":11.5,"posY":1.5,"rotX":0.0,"rotY":0.0,"rotZ":0.0,"scaleX":0.0,"scaleY":0.0},{"name":"Coin","posX":12.0,"posY":1.5,"rotX":0.0,"rotY":0.0,"rotZ":0.0,"scaleX":0.0,"scaleY":0.0},{"name":"Coin","posX":12.0,"posY":1.0,"rotX":0.0,"rotY":0.0,"rotZ":0.0,"scaleX":0.0,"scaleY":0.0},{"name":"PipeSmall","posX":19.0,"posY":-0.5,"rotX":0.0,"rotY":0.0,"rotZ":0.0,"scaleX":0.0,"scaleY":0.0},{"name":"PipeSmall","posX":22.5,"posY":-1.0,"rotX":0.0,"rotY":0.0,"rotZ":0.0,"scaleX":0.0,"scaleY":0.0},{"name":"PipeSmall","posX":25.0,"posY":-1.5,"rotX":0.0,"rotY":0.0,"rotZ":0.0,"scaleX":0.0,"scaleY":0.0},{"name":"PipeSmall","posX":29.049999237060548,"posY":-1.5,"rotX":0.0,"rotY":0.0,"rotZ":0.0,"scaleX":0.0,"scaleY":0.0},{"name":"PipeSmall","posX":32.81999969482422,"posY":-1.5199999809265137,"rotX":0.0,"rotY":0.0,"rotZ":0.0,"scaleX":0.0,"scaleY":0.0},{"name":"PipeSmall","posX":58.119998931884769,"posY":-1.5700000524520875,"rotX":0.0,"rotY":0.0,"rotZ":0.0,"scaleX":0.0,"scaleY":0.0},{"name":"PipeSmall","posX":35.779998779296878,"posY":-1.5,"rotX":0.0,"rotY":0.0,"rotZ":0.0,"scaleX":0.0,"scaleY":0.0},{"name":"PipeSmall","posX":38.459999084472659,"posY":-1.5,"rotX":0.0,"rotY":0.0,"rotZ":0.0,"scaleX":0.0,"scaleY":0.0},{"name":"PipeSmall","posX":46.0,"posY":-1.5,"rotX":0.0,"rotY":0.0,"rotZ":0.0,"scaleX":0.0,"scaleY":0.0},{"name":"PipeSmall","posX":50.560001373291019,"posY":-1.5,"rotX":0.0,"rotY":0.0,"rotZ":0.0,"scaleX":0.0,"scaleY":0.0},{"name":"PipeSmall","posX":55.0,"posY":-1.5,"rotX":0.0,"rotY":0.0,"rotZ":0.0,"scaleX":0.0,"scaleY":0.0},{"name":"PipeSmall","posX":60.5099983215332,"posY":-1.5700000524520875,"rotX":0.0,"rotY":0.0,"rotZ":0.0,"scaleX":0.0,"scaleY":0.0},{"name":"Saw","posX":44.5,"posY":-1.1299999952316285,"rotX":0.0,"rotY":0.0,"rotZ":0.0,"scaleX":0.0,"scaleY":0.0},{"name":"Saw","posX":44.5,"posY":-1.6299999952316285,"rotX":0.0,"rotY":0.0,"rotZ":0.0,"scaleX":0.0,"scaleY":0.0},{"name":"Saw","posX":49.349998474121097,"posY":-0.7799999713897705,"rotX":0.0,"rotY":0.0,"rotZ":0.0,"scaleX":0.0,"scaleY":0.0},{"name":"Saw","posX":47.02000045776367,"posY":-0.7699999809265137,"rotX":0.0,"rotY":0.0,"rotZ":0.0,"scaleX":0.0,"scaleY":0.0},{"name":"SmallHouse","posX":65.5,"posY":-3.0,"rotX":0.0,"rotY":0.0,"rotZ":0.0,"scaleX":0.0,"scaleY":0.0},{"name":"SmallHouse","posX":69.55000305175781,"posY":-3.0,"rotX":0.0,"rotY":0.0,"rotZ":0.0,"scaleX":0.0,"scaleY":0.0},{"name":"Steel","posX":68.0,"posY":0.5,"rotX":0.0,"rotY":0.0,"rotZ":0.0,"scaleX":0.0,"scaleY":0.0},{"name":"Steel","posX":127.08000183105469,"posY":-0.25,"rotX":0.0,"rotY":0.0,"rotZ":0.0,"scaleX":0.0,"scaleY":0.0},{"name":"Steel","posX":68.5,"posY":1.0,"rotX":0.0,"rotY":0.0,"rotZ":0.0,"scaleX":0.0,"scaleY":0.0},{"name":"ElectricOBstacle","posX":26.0,"posY":-0.5,"rotX":0.0,"rotY":0.0,"rotZ":0.0,"scaleX":0.0,"scaleY":0.0},{"name":"ElectricOBstacle","posX":27.979999542236329,"posY":-0.5,"rotX":0.0,"rotY":0.0,"rotZ":0.0,"scaleX":0.0,"scaleY":0.0},{"name":"HighHouse","posX":74.0,"posY":0.0,"rotX":0.0,"rotY":0.0,"rotZ":0.0,"scaleX":0.0,"scaleY":0.0},{"name":"HighHouse","posX":77.62000274658203,"posY":1.0,"rotX":0.0,"rotY":0.0,"rotZ":0.0,"scaleX":0.0,"scaleY":0.0},{"name":"HighHouse","posX":80.70999908447266,"posY":2.130000114440918,"rotX":0.0,"rotY":0.0,"rotZ":0.0,"scaleX":0.0,"scaleY":0.0},{"name":"VeryLongHouse","posX":136.5,"posY":-1.0,"rotX":0.0,"rotY":0.0,"rotZ":0.0,"scaleX":0.0,"scaleY":0.0},{"name":"PipeSmall","posX":82.69000244140625,"posY":-0.4300000071525574,"rotX":0.0,"rotY":0.0,"rotZ":0.0,"scaleX":0.0,"scaleY":0.0},{"name":"PipeSmall","posX":89.0,"posY":-1.0,"rotX":0.0,"rotY":0.0,"rotZ":0.0,"scaleX":0.0,"scaleY":0.0},{"name":"PipeSmall","posX":92.5,"posY":-1.0,"rotX":0.0,"rotY":0.0,"rotZ":0.0,"scaleX":0.0,"scaleY":0.0},{"name":"ElectricOBstacle","posX":132.4600067138672,"posY":1.2999999523162842,"rotX":0.0,"rotY":0.0,"rotZ":330.0,"scaleX":0.0,"scaleY":0.0},{"name":"Coin","posX":121.0,"posY":2.5,"rotX":0.0,"rotY":0.0,"rotZ":0.0,"scaleX":0.0,"scaleY":0.0},{"name":"Saw","posX":140.0,"posY":1.0,"rotX":0.0,"rotY":0.0,"rotZ":0.0,"scaleX":0.0,"scaleY":0.0},{"name":"Finish","posX":142.0,"posY":1.5,"rotX":0.0,"rotY":0.0,"rotZ":0.0,"scaleX":0.0,"scaleY":0.0},{"name":"Finish","posX":333.5,"posY":-2.5,"rotX":0.0,"rotY":0.0,"rotZ":0.0,"scaleX":0.0,"scaleY":0.0},{"name":"Coin","posX":43.0,"posY":2.0,"rotX":0.0,"rotY":0.0,"rotZ":0.0,"scaleX":0.0,"scaleY":0.0},{"name":"Coin","posX":42.5,"posY":2.0,"rotX":0.0,"rotY":0.0,"rotZ":0.0,"scaleX":0.0,"scaleY":0.0},{"name":"Coin","posX":42.5,"posY":1.5,"rotX":0.0,"rotY":0.0,"rotZ":0.0,"scaleX":0.0,"scaleY":0.0},{"name":"Coin","posX":43.5,"posY":1.5,"rotX":0.0,"rotY":0.0,"rotZ":0.0,"scaleX":0.0,"scaleY":0.0},{"name":"Coin","posX":31.5,"posY":2.0,"rotX":0.0,"rotY":0.0,"rotZ":0.0,"scaleX":0.0,"scaleY":0.0},{"name":"Coin","posX":32.5,"posY":2.0,"rotX":0.0,"rotY":0.0,"rotZ":0.0,"scaleX":0.0,"scaleY":0.0},{"name":"Coin","posX":32.0,"posY":2.0,"rotX":0.0,"rotY":0.0,"rotZ":0.0,"scaleX":0.0,"scaleY":0.0},{"name":"Coin","posX":31.5,"posY":1.5,"rotX":0.0,"rotY":0.0,"rotZ":0.0,"scaleX":0.0,"scaleY":0.0},{"name":"Coin","posX":32.0,"posY":1.5,"rotX":0.0,"rotY":0.0,"rotZ":0.0,"scaleX":0.0,"scaleY":0.0},{"name":"Coin","posX":32.5,"posY":1.5,"rotX":0.0,"rotY":0.0,"rotZ":0.0,"scaleX":0.0,"scaleY":0.0},{"name":"Coin","posX":43.5,"posY":2.0,"rotX":0.0,"rotY":0.0,"rotZ":0.0,"scaleX":0.0,"scaleY":0.0},{"name":"Coin","posX":76.38999938964844,"posY":1.0,"rotX":0.0,"rotY":0.0,"rotZ":0.0,"scaleX":0.0,"scaleY":0.0},{"name":"Coin","posX":76.41999816894531,"posY":1.5,"rotX":0.0,"rotY":0.0,"rotZ":0.0,"scaleX":0.0,"scaleY":0.0},{"name":"Coin","posX":76.01000213623047,"posY":1.5,"rotX":0.0,"rotY":0.0,"rotZ":0.0,"scaleX":0.0,"scaleY":0.0},{"name":"Coin","posX":75.9800033569336,"posY":1.0,"rotX":0.0,"rotY":0.0,"rotZ":0.0,"scaleX":0.0,"scaleY":0.0},{"name":"Coin","posX":83.5,"posY":4.5,"rotX":0.0,"rotY":0.0,"rotZ":0.0,"scaleX":0.0,"scaleY":0.0},{"name":"Coin","posX":84.0,"posY":4.5,"rotX":0.0,"rotY":0.0,"rotZ":0.0,"scaleX":0.0,"scaleY":0.0},{"name":"Coin","posX":84.0,"posY":4.0,"rotX":0.0,"rotY":0.0,"rotZ":0.0,"scaleX":0.0,"scaleY":0.0},{"name":"Coin","posX":83.5,"posY":4.0,"rotX":0.0,"rotY":0.0,"rotZ":0.0,"scaleX":0.0,"scaleY":0.0},{"name":"Coin","posX":87.5,"posY":0.5,"rotX":0.0,"rotY":0.0,"rotZ":0.0,"scaleX":0.0,"scaleY":0.0},{"name":"Coin","posX":88.0,"posY":0.5,"rotX":0.0,"rotY":0.0,"rotZ":0.0,"scaleX":0.0,"scaleY":0.0},{"name":"Coin","posX":88.0,"posY":0.0,"rotX":0.0,"rotY":0.0,"rotZ":0.0,"scaleX":0.0,"scaleY":0.0},{"name":"Coin","posX":87.5,"posY":0.0,"rotX":0.0,"rotY":0.0,"rotZ":0.0,"scaleX":0.0,"scaleY":0.0},{"name":"Coin","posX":91.5,"posY":0.5,"rotX":0.0,"rotY":0.0,"rotZ":0.0,"scaleX":0.0,"scaleY":0.0},{"name":"Coin","posX":91.5,"posY":0.0,"rotX":0.0,"rotY":0.0,"rotZ":0.0,"scaleX":0.0,"scaleY":0.0},{"name":"Coin","posX":92.0,"posY":0.5,"rotX":0.0,"rotY":0.0,"rotZ":0.0,"scaleX":0.0,"scaleY":0.0},{"name":"Coin","posX":92.0,"posY":0.0,"rotX":0.0,"rotY":0.0,"rotZ":0.0,"scaleX":0.0,"scaleY":0.0},{"name":"Pipe","posX":107.0,"posY":1.5,"rotX":0.0,"rotY":0.0,"rotZ":0.0,"scaleX":0.0,"scaleY":0.0},{"name":"Pipe","posX":113.0,"posY":1.5,"rotX":0.0,"rotY":0.0,"rotZ":0.0,"scaleX":0.0,"scaleY":0.0},{"name":"ElectricOBstacle","posX":104.0,"posY":1.0,"rotX":0.0,"rotY":0.0,"rotZ":0.0,"scaleX":0.0,"scaleY":0.0},{"name":"Saw","posX":129.52999877929688,"posY":0.4000000059604645,"rotX":0.0,"rotY":0.0,"rotZ":0.0,"scaleX":0.0,"scaleY":0.0},{"name":"Saw","posX":98.0,"posY":0.5,"rotX":0.0,"rotY":0.0,"rotZ":0.0,"scaleX":0.0,"scaleY":0.0},{"name":"Saw","posX":101.5,"posY":0.5,"rotX":0.0,"rotY":0.0,"rotZ":0.0,"scaleX":0.0,"scaleY":0.0},{"name":"Saw","posX":107.20999908447266,"posY":-0.41999998688697817,"rotX":0.0,"rotY":0.0,"rotZ":0.0,"scaleX":0.0,"scaleY":0.0},{"name":"PipeSmall","posX":108.68000030517578,"posY":-1.0299999713897706,"rotX":0.0,"rotY":0.0,"rotZ":0.0,"scaleX":0.0,"scaleY":0.0},{"name":"PipeSmall","posX":111.45999908447266,"posY":-1.0,"rotX":0.0,"rotY":0.0,"rotZ":0.0,"scaleX":0.0,"scaleY":0.0},{"name":"PipeSmall","posX":114.0,"posY":-1.0,"rotX":0.0,"rotY":0.0,"rotZ":0.0,"scaleX":0.0,"scaleY":0.0},{"name":"PipeSmall","posX":116.5,"posY":-1.0,"rotX":0.0,"rotY":0.0,"rotZ":0.0,"scaleX":0.0,"scaleY":0.0},{"name":"PipeSmall","posX":118.98999786376953,"posY":-1.0,"rotX":0.0,"rotY":0.0,"rotZ":0.0,"scaleX":0.0,"scaleY":0.0},{"name":"PipeSmall","posX":122.5,"posY":-1.0,"rotX":0.0,"rotY":0.0,"rotZ":0.0,"scaleX":0.0,"scaleY":0.0},{"name":"Coin","posX":110.0,"posY":2.5,"rotX":0.0,"rotY":0.0,"rotZ":0.0,"scaleX":0.0,"scaleY":0.0},{"name":"Coin","posX":110.5,"posY":2.5,"rotX":0.0,"rotY":0.0,"rotZ":0.0,"scaleX":0.0,"scaleY":0.0},{"name":"Coin","posX":110.5,"posY":2.0,"rotX":0.0,"rotY":0.0,"rotZ":0.0,"scaleX":0.0,"scaleY":0.0},{"name":"Coin","posX":110.0,"posY":2.0,"rotX":0.0,"rotY":0.0,"rotZ":0.0,"scaleX":0.0,"scaleY":0.0},{"name":"Coin","posX":112.0,"posY":3.0,"rotX":0.0,"rotY":0.0,"rotZ":0.0,"scaleX":0.0,"scaleY":0.0},{"name":"Coin","posX":112.0,"posY":3.5,"rotX":0.0,"rotY":0.0,"rotZ":0.0,"scaleX":0.0,"scaleY":0.0},{"name":"Coin","posX":112.5,"posY":3.5,"rotX":0.0,"rotY":0.0,"rotZ":0.0,"scaleX":0.0,"scaleY":0.0},{"name":"Coin","posX":112.5,"posY":3.0,"rotX":0.0,"rotY":0.0,"rotZ":0.0,"scaleX":0.0,"scaleY":0.0},{"name":"Coin","posX":115.0,"posY":3.0,"rotX":0.0,"rotY":0.0,"rotZ":0.0,"scaleX":0.0,"scaleY":0.0},{"name":"Coin","posX":115.5,"posY":3.5,"rotX":0.0,"rotY":0.0,"rotZ":0.0,"scaleX":0.0,"scaleY":0.0},{"name":"Coin","posX":115.5,"posY":2.5,"rotX":0.0,"rotY":0.0,"rotZ":0.0,"scaleX":0.0,"scaleY":0.0},{"name":"Coin","posX":115.5,"posY":3.0,"rotX":0.0,"rotY":0.0,"rotZ":0.0,"scaleX":0.0,"scaleY":0.0},{"name":"Coin","posX":115.0,"posY":3.5,"rotX":0.0,"rotY":0.0,"rotZ":0.0,"scaleX":0.0,"scaleY":0.0},{"name":"Coin","posX":115.0,"posY":2.5,"rotX":0.0,"rotY":0.0,"rotZ":0.0,"scaleX":0.0,"scaleY":0.0},{"name":"Coin","posX":120.0,"posY":2.5,"rotX":0.0,"rotY":0.0,"rotZ":0.0,"scaleX":0.0,"scaleY":0.0},{"name":"Coin","posX":120.5,"posY":2.5,"rotX":0.0,"rotY":0.0,"rotZ":0.0,"scaleX":0.0,"scaleY":0.0},{"name":"Coin","posX":253.5,"posY":1.0,"rotX":0.0,"rotY":0.0,"rotZ":0.0,"scaleX":0.0,"scaleY":0.0},{"name":"Coin","posX":70.5,"posY":-0.5,"rotX":0.0,"rotY":0.0,"rotZ":0.0,"scaleX":0.0,"scaleY":0.0},{"name":"PipeSmall","posX":43.0,"posY":-2.319999933242798,"rotX":0.0,"rotY":0.0,"rotZ":0.0,"scaleX":0.0,"scaleY":0.0},{"name":"PipeSmall","posX":86.5,"posY":-1.0,"rotX":0.0,"rotY":0.0,"rotZ":0.0,"scaleX":0.0,"scaleY":0.0},{"name":"PipeSmall","posX":48.27000045776367,"posY":-2.130000114440918,"rotX":0.0,"rotY":0.0,"rotZ":0.0,"scaleX":0.0,"scaleY":0.0},{"name":"PipeSmall","posX":72.20999908447266,"posY":-0.8399999737739563,"rotX":0.0,"rotY":0.0,"rotZ":0.0,"scaleX":0.0,"scaleY":0.0},{"name":"PipeSmall","posX":53.0,"posY":-2.0,"rotX":0.0,"rotY":0.0,"rotZ":0.0,"scaleX":0.0,"scaleY":0.0},{"name":"PipeSmall","posX":72.58000183105469,"posY":-0.5,"rotX":0.0,"rotY":0.0,"rotZ":0.0,"scaleX":0.0,"scaleY":0.0},{"name":"PipeSmall","posX":63.970001220703128,"posY":-1.4900000095367432,"rotX":0.0,"rotY":0.0,"rotZ":0.0,"scaleX":0.0,"scaleY":0.0},{"name":"PipeSmall","posX":84.5,"posY":-1.5,"rotX":0.0,"rotY":0.0,"rotZ":0.0,"scaleX":0.0,"scaleY":0.0},{"name":"Spring","posX":48.290000915527347,"posY":-1.090000033378601,"rotX":0.0,"rotY":0.0,"rotZ":0.0,"scaleX":0.0,"scaleY":0.0},{"name":"Spring","posX":60.5,"posY":-1.5,"rotX":0.0,"rotY":0.0,"rotZ":0.0,"scaleX":0.0,"scaleY":0.0},{"name":"Spring","posX":3.7100000381469728,"posY":0.0,"rotX":0.0,"rotY":0.0,"rotZ":0.0,"scaleX":0.0,"scaleY":0.0},{"name":"Spring","posX":14.5,"posY":0.6800000071525574,"rotX":0.0,"rotY":0.0,"rotZ":0.0,"scaleX":0.0,"scaleY":0.0},{"name":"Spring","posX":95.4800033569336,"posY":0.07000000029802323,"rotX":0.0,"rotY":0.0,"rotZ":0.0,"scaleX":0.0,"scaleY":0.0},{"name":"ElectricOBstacle","posX":135.1699981689453,"posY":1.350000023841858,"rotX":0.0,"rotY":0.0,"rotZ":330.0,"scaleX":0.0,"scaleY":0.0}]}